odoo8_addon_account_payment_order_to_voucher-8.0.1.0.0.99.dev14-py2.7-nspkg.pth
odoo8_addon_account_payment_order_to_voucher-8.0.1.0.0.99.dev14.dist-info/METADATA
odoo8_addon_account_payment_order_to_voucher-8.0.1.0.0.99.dev14.dist-info/RECORD
odoo8_addon_account_payment_order_to_voucher-8.0.1.0.0.99.dev14.dist-info/WHEEL
odoo8_addon_account_payment_order_to_voucher-8.0.1.0.0.99.dev14.dist-info/namespace_packages.txt
odoo8_addon_account_payment_order_to_voucher-8.0.1.0.0.99.dev14.dist-info/top_level.txt
odoo_addons/account_payment_order_to_voucher/README.rst
odoo_addons/account_payment_order_to_voucher/__init__.py
odoo_addons/account_payment_order_to_voucher/__openerp__.py
odoo_addons/account_payment_order_to_voucher/i18n/account_payment_order_to_voucher.pot
odoo_addons/account_payment_order_to_voucher/i18n/ca.po
odoo_addons/account_payment_order_to_voucher/i18n/de.po
odoo_addons/account_payment_order_to_voucher/i18n/es.po
odoo_addons/account_payment_order_to_voucher/i18n/fi.po
odoo_addons/account_payment_order_to_voucher/i18n/fr.po
odoo_addons/account_payment_order_to_voucher/i18n/it.po
odoo_addons/account_payment_order_to_voucher/i18n/pt_BR.po
odoo_addons/account_payment_order_to_voucher/i18n/sl.po
odoo_addons/account_payment_order_to_voucher/models/__init__.py
odoo_addons/account_payment_order_to_voucher/models/payment_order.py
odoo_addons/account_payment_order_to_voucher/static/description/icon.png
odoo_addons/account_payment_order_to_voucher/tests/__init__.py
odoo_addons/account_payment_order_to_voucher/tests/test_payment_order.py
odoo_addons/account_payment_order_to_voucher/views/payment_order_view.xml
